openseespyvis/Get_Rendering.py
openseespyvis/__init__.py
openseespyvis/internal_database_functions.py
openseespyvis/internal_plotting_functions.py
openseespyvis-0.0.6.dist-info/LICENSE
openseespyvis-0.0.6.dist-info/METADATA
openseespyvis-0.0.6.dist-info/WHEEL
openseespyvis-0.0.6.dist-info/top_level.txt
openseespyvis-0.0.6.dist-info/RECORD
