Metadata-Version: 2.1
Name: openseespyvis
Version: 0.0.6
Summary: A development package of openseespy visualization commands.
Home-page: https://github.com/u-anurag/openseespyvis
Author: anurag upadhyay
Author-email: iitg.anurag@gmail.com
License: UNKNOWN
Platform: UNKNOWN
Classifier: Programming Language :: Python :: 3
Classifier: License :: OSI Approved :: MIT License
Classifier: Operating System :: OS Independent
Requires-Python: >=3.6
